ai_make_music/__init__.py
ai_make_music-1767667.326.381.dist-info/licenses/LICENSE
ai_make_music-1767667.326.381.dist-info/METADATA
ai_make_music-1767667.326.381.dist-info/WHEEL
ai_make_music-1767667.326.381.dist-info/top_level.txt
ai_make_music-1767667.326.381.dist-info/RECORD
