Metadata-Version: 2.4
Name: ai-make-music
Version: 1767667.326.381
Summary: High-quality integration for https://supermaker.ai/music/ai-make-music/
Home-page: https://supermaker.ai/music/ai-make-music/
Author: SuperMaker
Classifier: Programming Language :: Python :: 3
Classifier: License :: OSI Approved :: MIT License
Requires-Python: >=3.6
License-File: LICENSE
Dynamic: author
Dynamic: classifier
Dynamic: description
Dynamic: description-content-type
Dynamic: home-page
Dynamic: license-file
Dynamic: requires-python
Dynamic: summary
